jhu_csse/__init__.py
jhu_csse-0.0.1.dist-info/LICENSE
jhu_csse-0.0.1.dist-info/WHEEL
jhu_csse-0.0.1.dist-info/METADATA
jhu_csse-0.0.1.dist-info/RECORD
